{
	"credit": "Made with Blockbench",
	"parent": "idyllic_food_diary:block/cooking_pot",
	"render_type": "minecraft:cutout",
	"textures": {
		"0": "idyllic_food_diary:block/cooking_pot_bottom",
		"1": "idyllic_food_diary:block/cooking_pot_side",
		"2": "idyllic_food_diary:block/cooking_pot_top",
		"3": "idyllic_food_diary:block/cooking_pot_parts",
		"particle": "idyllic_food_diary:block/cooking_pot_bottom"
	},
	"elements": [
		{
			"name": "left_handle",
			"from": [14, 9, 5],
			"to": [16, 11, 11],
			"rotation": {"angle": 0, "axis": "y", "origin": [11, 7, -1]},
			"faces": {
				"north": {"uv": [12, 0, 14, 2], "texture": "#3"},
				"east": {"uv": [6, 0, 12, 2], "texture": "#3"},
				"south": {"uv": [4, 0, 6, 2], "texture": "#3"},
				"up": {"uv": [14, 6, 16, 12], "texture": "#3"},
				"down": {"uv": [14, 0, 16, 6], "texture": "#3"}
			}
		},
		{
			"name": "right_handle",
			"from": [0, 9, 5],
			"to": [2, 11, 11],
			"rotation": {"angle": 0, "axis": "y", "origin": [-3, 7, -1]},
			"faces": {
				"north": {"uv": [4, 0, 6, 2], "texture": "#3"},
				"south": {"uv": [12, 0, 14, 2], "texture": "#3"},
				"west": {"uv": [6, 0, 12, 2], "texture": "#3"},
				"up": {"uv": [16, 6, 14, 12], "texture": "#3"},
				"down": {"uv": [16, 0, 14, 6], "texture": "#3"}
			}
		},
		{
			"name": "bottom",
			"from": [4, 0, 4],
			"to": [12, 2, 12],
			"rotation": {"angle": 0, "axis": "y", "origin": [2, 0, 2]},
			"faces": {
				"up": {"uv": [4, 4, 12, 12], "texture": "#2"},
				"down": {"uv": [4, 4, 12, 12], "texture": "#0"}
			}
		},
		{
			"from": [2, 0, 4],
			"to": [4, 13, 12],
			"faces": {
				"east": {"uv": [4, 3, 12, 16], "texture": "#1"},
				"west": {"uv": [4, 3, 12, 16], "texture": "#1"},
				"up": {"uv": [2, 4, 4, 12], "texture": "#2"},
				"down": {"uv": [2, 4, 4, 12], "texture": "#0"}
			}
		},
		{
			"from": [2, 0, 12],
			"to": [14, 13, 14],
			"rotation": {"angle": 0, "axis": "y", "origin": [0, 0, 1]},
			"faces": {
				"north": {"uv": [1, 3, 13, 16], "texture": "#1"},
				"east": {"uv": [2, 3, 4, 16], "texture": "#1"},
				"south": {"uv": [2, 3, 14, 16], "texture": "#1"},
				"west": {"uv": [12, 3, 14, 16], "texture": "#1"},
				"up": {"uv": [2, 12, 14, 14], "texture": "#2"},
				"down": {"uv": [2, 2, 14, 4], "texture": "#0"}
			}
		},
		{
			"from": [2, 0, 2],
			"to": [14, 13, 4],
			"rotation": {"angle": 0, "axis": "y", "origin": [0, 0, -10]},
			"faces": {
				"north": {"uv": [2, 3, 14, 16], "texture": "#1"},
				"east": {"uv": [12, 3, 14, 16], "texture": "#1"},
				"south": {"uv": [2, 3, 14, 16], "texture": "#1"},
				"west": {"uv": [2, 3, 4, 16], "texture": "#1"},
				"up": {"uv": [2, 2, 14, 4], "texture": "#2"},
				"down": {"uv": [2, 12, 14, 14], "texture": "#0"}
			}
		},
		{
			"from": [12, 0, 4],
			"to": [14, 13, 12],
			"rotation": {"angle": 0, "axis": "y", "origin": [11, 0, 0]},
			"faces": {
				"east": {"uv": [4, 3, 12, 16], "texture": "#1"},
				"west": {"uv": [4, 3, 12, 16], "texture": "#1"},
				"up": {"uv": [12, 4, 14, 12], "texture": "#2"},
				"down": {"uv": [12, 4, 14, 12], "texture": "#0"}
			}
		}
	],
	"display": {
		"thirdperson_righthand": {
			"rotation": [65, 180, 0],
			"translation": [0, 3.5, 0.75],
			"scale": [0.65, 0.65, 0.65]
		},
		"thirdperson_lefthand": {
			"rotation": [65, 180, 0],
			"translation": [0, 3.5, 0.75],
			"scale": [0.65, 0.65, 0.65]
		},
		"firstperson_righthand": {
			"rotation": [0, 180, 0],
			"translation": [0, 1, 0],
			"scale": [0.7, 0.7, 0.7]
		},
		"firstperson_lefthand": {
			"rotation": [0, 180, 0],
			"translation": [0, 1, 0],
			"scale": [0.7, 0.7, 0.7]
		},
		"ground": {
			"translation": [0, 3.25, 0],
			"scale": [0.5, 0.5, 0.5]
		},
		"gui": {
			"rotation": [30, -135, 0],
			"translation": [0, 0.75, 0],
			"scale": [0.75, 0.75, 0.75]
		},
		"head": {
			"rotation": [0, 180, 0],
			"translation": [0, 14.5, 0]
		}
	}
}